{
    "openapi": "3.0.0",
    "info": {
        "title": "Pet Shop API",
        "version": "1.0.0"
    },
    "paths": {
        "/api/v1/admin/login": {
            "post": {
                "tags": [
                    "Admin"
                ],
                "summary": "Admin Login",
                "description": "Admin Login here",
                "operationId": "Login",
                "requestBody": {
                    "content": {
                        "application/x-www-form-urlencoded": {
                            "schema": {
                                "required": [
                                    "email",
                                    "password"
                                ],
                                "properties": {
                                    "email": {
                                        "type": "password"
                                    },
                                    "password": {
                                        "type": "password"
                                    }
                                },
                                "type": "object"
                            }
                        },
                        "application/json": {
                            "schema": {}
                        }
                    }
                },
                "responses": {
                    "200": {
                        "description": "Login Successfully",
                        "content": {
                            "application/json": {
                                "schema": {}
                            }
                        }
                    },
                    "422": {
                        "description": "Unprocessable Entity",
                        "content": {
                            "application/json": {
                                "schema": {}
                            }
                        }
                    },
                    "400": {
                        "description": "Bad request"
                    },
                    "404": {
                        "description": "Resource Not Found"
                    }
                }
            }
        },
        "/api/v1/user/forget-password": {
            "post": {
                "tags": [
                    "User"
                ],
                "summary": "Create token for resetting  Password",
                "description": "Request password reset token",
                "operationId": "forgetPassword",
                "requestBody": {
                    "content": {
                        "application/x-www-form-urlencoded": {
                            "schema": {
                                "required": [
                                    "email"
                                ],
                                "properties": {
                                    "email": {
                                        "type": "text"
                                    }
                                },
                                "type": "object"
                            }
                        },
                        "application/json": {
                            "schema": {}
                        }
                    }
                },
                "responses": {
                    "201": {
                        "description": "Password reset requested successfully",
                        "content": {
                            "application/json": {
                                "schema": {}
                            }
                        }
                    },
                    "422": {
                        "description": "Unprocessable Entity",
                        "content": {
                            "application/json": {
                                "schema": {}
                            }
                        }
                    },
                    "400": {
                        "description": "Bad request"
                    },
                    "404": {
                        "description": "Resource Not Found"
                    }
                }
            }
        },
        "/api/v1/user/login": {
            "post": {
                "tags": [
                    "User"
                ],
                "summary": "User Login",
                "description": "User Login here",
                "operationId": "Login",
                "requestBody": {
                    "content": {
                        "application/x-www-form-urlencoded": {
                            "schema": {
                                "required": [
                                    "email",
                                    "password"
                                ],
                                "properties": {
                                    "email": {
                                        "type": "password"
                                    },
                                    "password": {
                                        "type": "password"
                                    }
                                },
                                "type": "object"
                            }
                        },
                        "application/json": {
                            "schema": {}
                        }
                    }
                },
                "responses": {
                    "200": {
                        "description": "Login Successfully",
                        "content": {
                            "application/json": {
                                "schema": {}
                            }
                        }
                    },
                    "422": {
                        "description": "Unprocessable Entity",
                        "content": {
                            "application/json": {
                                "schema": {}
                            }
                        }
                    },
                    "400": {
                        "description": "Bad request"
                    },
                    "404": {
                        "description": "Resource Not Found"
                    }
                }
            }
        },
        "/api/v1/user/logout": {
            "get": {
                "tags": [
                    "User"
                ],
                "summary": "User Logout",
                "description": "User Logout here",
                "operationId": "Logout",
                "responses": {
                    "201": {
                        "description": "User logout",
                        "content": {
                            "application/json": {
                                "schema": {}
                            }
                        }
                    },
                    "422": {
                        "description": "Unprocessable Entity",
                        "content": {
                            "application/json": {
                                "schema": {}
                            }
                        }
                    },
                    "400": {
                        "description": "Bad request"
                    },
                    "404": {
                        "description": "Resource Not Found"
                    }
                },
                "security": [
                    {
                        "bearer_token": []
                    }
                ]
            }
        },
        "/api/v1/user/create": {
            "post": {
                "tags": [
                    "User"
                ],
                "summary": "User Register",
                "description": "User Register here",
                "operationId": "Register",
                "requestBody": {
                    "content": {
                        "multipart/form-data": {
                            "schema": {
                                "required": [
                                    "first_name",
                                    "last_name",
                                    "email",
                                    "password",
                                    "password_confirmation",
                                    "address",
                                    "phone_number"
                                ],
                                "properties": {
                                    "first_name": {
                                        "type": "text"
                                    },
                                    "last_name": {
                                        "type": "text"
                                    },
                                    "email": {
                                        "type": "text"
                                    },
                                    "password": {
                                        "type": "password"
                                    },
                                    "password_confirmation": {
                                        "type": "password"
                                    },
                                    "avatar": {
                                        "type": "text"
                                    },
                                    "address": {
                                        "type": "text"
                                    },
                                    "phone_number": {
                                        "type": "text"
                                    },
                                    "is_marketing": {
                                        "type": "text"
                                    }
                                },
                                "type": "object"
                            }
                        },
                        "application/json": {
                            "schema": {}
                        }
                    }
                },
                "responses": {
                    "201": {
                        "description": "Register Successfully",
                        "content": {
                            "application/json": {
                                "schema": {}
                            }
                        }
                    },
                    "422": {
                        "description": "Unprocessable Entity",
                        "content": {
                            "application/json": {
                                "schema": {}
                            }
                        }
                    },
                    "400": {
                        "description": "Bad request"
                    },
                    "404": {
                        "description": "Resource Not Found"
                    }
                }
            }
        },
        "/api/v1/user/reset-password-token": {
            "post": {
                "tags": [
                    "User"
                ],
                "summary": "Provide token and change your password",
                "description": "User Change password",
                "operationId": "resetPassword",
                "requestBody": {
                    "content": {
                        "application/x-www-form-urlencoded": {
                            "schema": {
                                "required": [
                                    "token",
                                    "email",
                                    "password",
                                    "password_confirmation"
                                ],
                                "properties": {
                                    "token": {
                                        "type": "text"
                                    },
                                    "email": {
                                        "type": "text"
                                    },
                                    "password": {
                                        "type": "password"
                                    },
                                    "password_confirmation": {
                                        "type": "password"
                                    }
                                },
                                "type": "object"
                            }
                        },
                        "application/json": {
                            "schema": {}
                        }
                    }
                },
                "responses": {
                    "201": {
                        "description": "Password changed Successfully",
                        "content": {
                            "application/json": {
                                "schema": {}
                            }
                        }
                    },
                    "422": {
                        "description": "Unprocessable Entity",
                        "content": {
                            "application/json": {
                                "schema": {}
                            }
                        }
                    },
                    "400": {
                        "description": "Bad request"
                    },
                    "404": {
                        "description": "Resource Not Found"
                    }
                }
            }
        },
        "/api/v1/categories": {
            "get": {
                "tags": [
                    "Categories"
                ],
                "summary": "List all Categories",
                "description": "List all Categories",
                "operationId": "allCategories",
                "parameters": [
                    {
                        "name": "page",
                        "in": "query",
                        "schema": {
                            "type": "integer"
                        }
                    },
                    {
                        "name": "limit",
                        "in": "query",
                        "schema": {
                            "type": "integer"
                        }
                    },
                    {
                        "name": "sortBy",
                        "in": "query",
                        "schema": {
                            "type": "string"
                        }
                    },
                    {
                        "name": "desc",
                        "in": "query",
                        "schema": {
                            "type": "boolean"
                        }
                    }
                ],
                "responses": {
                    "200": {
                        "description": "User logout",
                        "content": {
                            "application/json": {
                                "schema": {}
                            }
                        }
                    },
                    "422": {
                        "description": "Unprocessable Entity",
                        "content": {
                            "application/json": {
                                "schema": {}
                            }
                        }
                    },
                    "400": {
                        "description": "Bad request"
                    },
                    "404": {
                        "description": "Resource Not Found"
                    }
                }
            }
        },
        "/api/v1/file/{uuid}": {
            "get": {
                "tags": [
                    "File"
                ],
                "summary": "User can download file",
                "description": "User can download file",
                "operationId": "downloadFile",
                "parameters": [
                    {
                        "name": "uuid",
                        "in": "path",
                        "schema": {
                            "type": "string"
                        }
                    }
                ],
                "responses": {
                    "200": {
                        "description": "File downloaded successfully.",
                        "content": {
                            "application/json": {
                                "schema": {}
                            }
                        }
                    },
                    "422": {
                        "description": "Unprocessable Entity",
                        "content": {
                            "application/json": {
                                "schema": {}
                            }
                        }
                    },
                    "400": {
                        "description": "Bad request"
                    },
                    "404": {
                        "description": "Resource Not Found"
                    }
                }
            }
        },
        "/api/v1/file/upload": {
            "post": {
                "tags": [
                    "File"
                ],
                "summary": "File Upload",
                "description": "User can upload file here",
                "operationId": "uploadFile",
                "requestBody": {
                    "content": {
                        "multipart/form-data": {
                            "schema": {
                                "required": [
                                    "file"
                                ],
                                "properties": {
                                    "file": {
                                        "type": "file"
                                    }
                                },
                                "type": "object"
                            }
                        },
                        "application/json": {
                            "schema": {}
                        }
                    }
                },
                "responses": {
                    "201": {
                        "description": "File uploaded Successfully",
                        "content": {
                            "application/json": {
                                "schema": {}
                            }
                        }
                    },
                    "422": {
                        "description": "Unprocessable Entity",
                        "content": {
                            "application/json": {
                                "schema": {}
                            }
                        }
                    },
                    "400": {
                        "description": "Bad request"
                    },
                    "404": {
                        "description": "Resource Not Found"
                    }
                },
                "security": [
                    {
                        "bearer_token": []
                    }
                ]
            }
        },
        "/api/v1/product/create": {
            "post": {
                "tags": [
                    "Products"
                ],
                "summary": "Create Product",
                "description": "Create new Product",
                "operationId": "CreateProduct",
                "requestBody": {
                    "content": {
                        "application/x-www-form-urlencoded": {
                            "schema": {
                                "required": [
                                    "category_uuid",
                                    "title",
                                    "price",
                                    "description",
                                    "metadata"
                                ],
                                "properties": {
                                    "category_uuid": {
                                        "type": "text"
                                    },
                                    "title": {
                                        "type": "text"
                                    },
                                    "price": {
                                        "type": "number"
                                    },
                                    "description": {
                                        "type": "text"
                                    },
                                    "metadata": {
                                        "type": "object",
                                        "example": {
                                            "image": "string",
                                            "brand": "string"
                                        }
                                    }
                                },
                                "type": "object"
                            }
                        },
                        "application/json": {
                            "schema": {}
                        }
                    }
                },
                "responses": {
                    "201": {
                        "description": "Product created successfully",
                        "content": {
                            "application/json": {
                                "schema": {}
                            }
                        }
                    },
                    "422": {
                        "description": "Unprocessable Entity",
                        "content": {
                            "application/json": {
                                "schema": {}
                            }
                        }
                    },
                    "400": {
                        "description": "Bad request"
                    },
                    "404": {
                        "description": "Resource Not Found"
                    }
                },
                "security": [
                    {
                        "bearer_token": []
                    }
                ]
            }
        },
        "/api/v1/product/{uuid}": {
            "get": {
                "tags": [
                    "Products"
                ],
                "summary": "Display fetched product",
                "description": "Display fetched product",
                "operationId": "singleProduct",
                "parameters": [
                    {
                        "name": "uuid",
                        "in": "path",
                        "schema": {
                            "type": "string"
                        }
                    }
                ],
                "responses": {
                    "200": {
                        "description": "Display fetched product",
                        "content": {
                            "application/json": {
                                "schema": {}
                            }
                        }
                    },
                    "422": {
                        "description": "Unprocessable Entity",
                        "content": {
                            "application/json": {
                                "schema": {}
                            }
                        }
                    },
                    "400": {
                        "description": "Bad request"
                    },
                    "404": {
                        "description": "Resource Not Found"
                    }
                },
                "security": [
                    {
                        "bearer_token": []
                    }
                ]
            },
            "put": {
                "tags": [
                    "Products"
                ],
                "summary": "Update product with uuid",
                "description": "update Product",
                "operationId": "updateProduct",
                "parameters": [
                    {
                        "name": "uuid",
                        "in": "path",
                        "schema": {
                            "type": "string"
                        }
                    }
                ],
                "requestBody": {
                    "content": {
                        "application/x-www-form-urlencoded": {
                            "schema": {
                                "required": [
                                    "category_uuid",
                                    "title",
                                    "price",
                                    "description",
                                    "metadata"
                                ],
                                "properties": {
                                    "category_uuid": {
                                        "type": "text"
                                    },
                                    "title": {
                                        "type": "text"
                                    },
                                    "price": {
                                        "type": "number"
                                    },
                                    "description": {
                                        "type": "text"
                                    },
                                    "metadata": {
                                        "type": "object",
                                        "example": {
                                            "image": "string",
                                            "brand": "string"
                                        }
                                    }
                                },
                                "type": "object"
                            }
                        },
                        "application/json": {
                            "schema": {}
                        }
                    }
                },
                "responses": {
                    "200": {
                        "description": "Product added successfully",
                        "content": {
                            "application/json": {
                                "schema": {}
                            }
                        }
                    },
                    "422": {
                        "description": "Unprocessable Entity",
                        "content": {
                            "application/json": {
                                "schema": {}
                            }
                        }
                    },
                    "400": {
                        "description": "Bad request"
                    },
                    "404": {
                        "description": "Resource Not Found"
                    }
                },
                "security": [
                    {
                        "bearer_token": []
                    }
                ]
            },
            "delete": {
                "tags": [
                    "Products"
                ],
                "summary": "Delete specific product",
                "description": "Delete specific product",
                "operationId": "deleteProduct",
                "parameters": [
                    {
                        "name": "uuid",
                        "in": "path",
                        "schema": {
                            "type": "string"
                        }
                    }
                ],
                "responses": {
                    "200": {
                        "description": "Product deleted successfully product",
                        "content": {
                            "application/json": {
                                "schema": {}
                            }
                        }
                    },
                    "422": {
                        "description": "Unprocessable Entity",
                        "content": {
                            "application/json": {
                                "schema": {}
                            }
                        }
                    },
                    "400": {
                        "description": "Bad request"
                    },
                    "404": {
                        "description": "Resource Not Found"
                    }
                },
                "security": [
                    {
                        "bearer_token": []
                    }
                ]
            }
        },
        "/api/v1/products": {
            "get": {
                "tags": [
                    "Products"
                ],
                "summary": "Show all products",
                "description": "Show all products",
                "operationId": "allProducts",
                "parameters": [
                    {
                        "name": "page",
                        "in": "query",
                        "schema": {
                            "type": "integer"
                        }
                    },
                    {
                        "name": "limit",
                        "in": "query",
                        "schema": {
                            "type": "integer"
                        }
                    },
                    {
                        "name": "sortBy",
                        "in": "query",
                        "schema": {
                            "type": "string"
                        }
                    },
                    {
                        "name": "desc",
                        "in": "query",
                        "schema": {
                            "type": "boolean"
                        }
                    }
                ],
                "responses": {
                    "200": {
                        "description": "User logout",
                        "content": {
                            "application/json": {
                                "schema": {}
                            }
                        }
                    },
                    "422": {
                        "description": "Unprocessable Entity",
                        "content": {
                            "application/json": {
                                "schema": {}
                            }
                        }
                    },
                    "400": {
                        "description": "Bad request"
                    },
                    "404": {
                        "description": "Resource Not Found"
                    }
                },
                "security": [
                    {
                        "bearer_token": []
                    }
                ]
            }
        },
        "/api/v1/user": {
            "get": {
                "tags": [
                    "User"
                ],
                "summary": "Display User Profile",
                "description": "View user profile single",
                "operationId": "profile",
                "responses": {
                    "201": {
                        "description": "Display User Profile",
                        "content": {
                            "application/json": {
                                "schema": {}
                            }
                        }
                    },
                    "422": {
                        "description": "Unprocessable Entity",
                        "content": {
                            "application/json": {
                                "schema": {}
                            }
                        }
                    },
                    "400": {
                        "description": "Bad request"
                    },
                    "404": {
                        "description": "Resource Not Found"
                    }
                },
                "security": [
                    {
                        "bearer_token": []
                    }
                ]
            },
            "delete": {
                "tags": [
                    "User"
                ],
                "summary": "User delete account",
                "description": "User delete account",
                "operationId": "DeleteUser",
                "responses": {
                    "201": {
                        "description": "User deleted successfully.",
                        "content": {
                            "application/json": {
                                "schema": {}
                            }
                        }
                    },
                    "422": {
                        "description": "Unprocessable Entity",
                        "content": {
                            "application/json": {
                                "schema": {}
                            }
                        }
                    },
                    "400": {
                        "description": "Bad request"
                    },
                    "404": {
                        "description": "Resource Not Found"
                    }
                },
                "security": [
                    {
                        "bearer_token": []
                    }
                ]
            }
        },
        "/api/v1/user/edit": {
            "put": {
                "tags": [
                    "User"
                ],
                "summary": "Update  user profile",
                "description": "User Update profile",
                "operationId": "Edit",
                "requestBody": {
                    "content": {
                        "application/x-www-form-urlencoded": {
                            "schema": {
                                "required": [
                                    "first_name",
                                    "last_name",
                                    "email",
                                    "password",
                                    "password_confirmation",
                                    "address",
                                    "phone_number"
                                ],
                                "properties": {
                                    "first_name": {
                                        "type": "text"
                                    },
                                    "last_name": {
                                        "type": "text"
                                    },
                                    "email": {
                                        "type": "text"
                                    },
                                    "password": {
                                        "type": "password"
                                    },
                                    "password_confirmation": {
                                        "type": "password"
                                    },
                                    "avatar": {
                                        "type": "text"
                                    },
                                    "address": {
                                        "type": "text"
                                    },
                                    "phone_number": {
                                        "type": "text"
                                    },
                                    "is_marketing": {
                                        "type": "text"
                                    }
                                },
                                "type": "object"
                            }
                        },
                        "application/json": {
                            "schema": {}
                        }
                    }
                },
                "responses": {
                    "201": {
                        "description": "Profile Updated Successfully",
                        "content": {
                            "application/json": {
                                "schema": {}
                            }
                        }
                    },
                    "422": {
                        "description": "Unprocessable Entity",
                        "content": {
                            "application/json": {
                                "schema": {}
                            }
                        }
                    },
                    "400": {
                        "description": "Bad request"
                    },
                    "404": {
                        "description": "Resource Not Found"
                    }
                },
                "security": [
                    {
                        "bearer_token": []
                    }
                ]
            }
        },
        "/api/v1/user/orders": {
            "get": {
                "tags": [
                    "User"
                ],
                "summary": "Show user order",
                "description": "User Logout here",
                "operationId": "userOrders",
                "parameters": [
                    {
                        "name": "page",
                        "in": "query",
                        "schema": {
                            "type": "integer"
                        }
                    },
                    {
                        "name": "limit",
                        "in": "query",
                        "schema": {
                            "type": "integer"
                        }
                    },
                    {
                        "name": "sortBy",
                        "in": "query",
                        "schema": {
                            "type": "string"
                        }
                    },
                    {
                        "name": "desc",
                        "in": "query",
                        "schema": {
                            "type": "boolean"
                        }
                    }
                ],
                "responses": {
                    "201": {
                        "description": "User logout",
                        "content": {
                            "application/json": {
                                "schema": {}
                            }
                        }
                    },
                    "422": {
                        "description": "Unprocessable Entity",
                        "content": {
                            "application/json": {
                                "schema": {}
                            }
                        }
                    },
                    "400": {
                        "description": "Bad request"
                    },
                    "404": {
                        "description": "Resource Not Found"
                    }
                },
                "security": [
                    {
                        "bearer_token": []
                    }
                ]
            }
        }
    },
    "components": {
        "securitySchemes": {
            "bearer_token": {
                "type": "http",
                "scheme": "bearer",
                "description": "Enter token in format (Bearer <token>)",
                "name": "Authorization",
                "in": "header"
            }
        }
    },
    "security": [
        []
    ]
}